{
  "scenes": [
    {
      "name": "Day",
      "video":      "data/videos/nD_1.mp4",
      "detections": "data/detections/scene_day.json",
      "condition":  "day"
    },
    {
      "name": "Rain",
      "video":      "data/videos/rD_2.mp4",
      "detections": "data/detections/scene_rain.json",
      "condition":  "rain"
    },
    {
      "name": "Night",
      "video":      "data/videos/nN_1.mp4",
      "detections": "data/detections/scene_night.json",
      "condition":  "night"
    }
  ],
  "playback": {
    "default_scene": 0,
    "loop": true
  },
  "threat": {
    "ttc_warning_threshold_s":  4.0,
    "ttc_critical_threshold_s": 2.0,
    "lateral_warning_m":  1.5,
    "lateral_critical_m": 0.8
  },
  "display": {
    "window_width":  1600,
    "window_height": 900,
    "video_panel_ratio": 0.65,
    "show_bev": true,
    "show_track_table": true
  }
}
